<?xml version="1.0" encoding="ISO-8859-1"?>
<npc name="Mood Neva" script="Default.lua" walkinterval="2000" floorchange="0">
	<health now="100" max="100" />
	<look type="128" head="116" body="119" legs="7" feet="116" addons="3" />
	<parameters>
		<parameter key="message_greet" value="Olá |PLAYERNAME|. Seja bem-vindo aos correios." />
		<parameter key="message_sendtrade" value="Deseja mandar algum presente?" /> 
		<parameter key="message_farewell" value="Adeus!" />
		<parameter key="message_walkaway" value="Nos vemos depois!" />
		<parameter key="module_shop" value="1" />
		<parameter key="shop_buyable" value="label,2599,1;parcel,2595,1;letter,2597,10" />
	</parameters>
</npc>