<?xml version="1.0" encoding="UTF-8"?>
<monster name="Enslaved Dwarf" nameDescription="an enslaved dwarf" race="blood" experience="2900" speed="280" manacost="0">
	<health now="4200" max="4200"/>
	<look type="494" corpse="17408"/>
	<targetchange interval="4000" chance="10"/>
	<flags>
		<flag summonable="0"/>
		<flag attackable="1"/>
		<flag hostile="1"/>
		<flag illusionable="0"/>
		<flag convinceable="0"/>
		<flag pushable="0"/>
		<flag canpushitems="1"/>
		<flag canpushcreatures="1"/>
		<flag targetdistance="1"/>
		<flag staticattack="70"/>
		<flag runonhealth="0"/>
	</flags>
	<attacks>
		<attack name="melee" interval="2000" skill="100" attack="91"/>
		<attack name="physical" interval="2000" chance="15" range="7" min="-0" max="-340">
			<attribute key="shootEffect" value="largerock"/>
		</attack>
		<attack name="physical" interval="2000" chance="10" range="7" target="1" radius="3" min="-0" max="-250">
			<attribute key="shootEffect" value="explosion"/>
			<attribute key="areaEffect" value="explosion"/>
		</attack>
		<attack name="drunk" interval="2000" chance="20" target="0" radius="5" duration="6000">
			<attribute key="areaEffect" value="yellowspark"/>
		</attack>
		<attack name="enslaved dwarf skill reducer 1" interval="2000" chance="5"/>
		<attack name="enslaved dwarf skill reducer 2" interval="2000" chance="5"/>
	</attacks>
	<defenses armor="30" defense="30">
		<defense name="healing" interval="2000" chance="10" min="396" max="478">
			<attribute key="areaEffect" value="greenshimmer"/>
		</defense>
	</defenses>
	<elements>
		<element energyPercent="10"/>
		<element icePercent="1"/>
		<element deathPercent="1"/>
		<element earthPercent="20"/>
	</elements>
	<immunities>
		<immunity fire="1"/>
		<immunity paralyze="1"/>
		<immunity invisible="1"/>
	</immunities>
	<voices interval="5000" chance="10">
		<voice sentence="Bark!"/>
		<voice sentence="Blood!"/>
	</voices>
	<loot>
		<item id="5880" countmax="1" chance="10000"/><!-- iron ore -->
		<item id="2350" countmax="1" chance="10000"/><!-- sword hilt -->
		<item id="20134" countmax="1" chance="10000"/><!-- mad froth -->
		<item id="20135" countmax="1" chance="10000"/><!-- red hair dye -->
		<item id="2150" countmax="1" chance="10000"/><!-- small amethist -->
		<item id="2149" countmax="1" chance="10000"/><!-- small emerald -->
		<item id="18417" countmax="1" chance="10000"/><!-- Brown crystal splinter -->
		<item id="18420" countmax="1" chance="10000"/><!-- red crystal fragment -->
		<item id="18416" countmax="1" chance="10000"/><!-- green crystal splinter -->
		<item id="11227" countmax="1" chance="10000"/><!-- shiny stone -->
	</loot>
</monster>
