<?xml version="1.0" encoding="UTF-8"?>
<monster name="Gang Member" nameDescription="a gang member" race="blood" experience="70" speed="200" manacost="420">
	<health now="295" max="295"/>
	<look type="151" head="114" body="19" legs="42" feet="20" corpse="20403"/>
	<targetchange interval="4000" chance="0"/>
	<strategy attack="100" defense="0"/>
	<flags>
		<flag summonable="0"/>
		<flag attackable="1"/>
		<flag hostile="1"/>
		<flag illusionable="1"/>
		<flag convinceable="1"/>
		<flag pushable="1"/>
		<flag canpushitems="0"/>
		<flag canpushcreatures="0"/>
		<flag staticattack="90"/>
		<flag targetdistance="1"/>
		<flag runonhealth="35"/>
	</flags>
	<attacks>
		<attack name="melee" interval="2000" skill="60" attack="20"/>
	</attacks>
	<defenses armor="15" defense="15"/>
	<elements>
		<element deathPercent="-5"/>
	</elements>
	<voices interval="5000" chance="10">
		<voice sentence="This is our territory!"/>
		<voice sentence="Help me guys!"/>
		<voice sentence="I don't like the way you look!"/>
		<voice sentence="You're wearing the wrong colours!"/>
		<voice sentence="Don't mess with us!"/>
	</voices>
	<loot>
		<item id="12382" countmax="1" chance="10000"/><!-- scribbled sheet of paper -->
		<item id="1987" countmax="1" chance="10000"/><!-- bag -->
		<item id="2148" countmax="1" chance="10000"/><!-- gold coin -->
		<item id="5913" countmax="1" chance="10000"/><!-- brown piece of cloth -->
		<item id="5909" countmax="1" chance="10000"/><!-- white piece of cloth -->
	</loot>
</monster>
